jmp/__init__.py
jmp/_src/__init__.py
jmp/_src/loss_scale.py
jmp/_src/loss_scale_test.py
jmp/_src/policy.py
jmp/_src/policy_test.py
jmp-0.0.4.dist-info/LICENSE
jmp-0.0.4.dist-info/METADATA
jmp-0.0.4.dist-info/WHEEL
jmp-0.0.4.dist-info/top_level.txt
jmp-0.0.4.dist-info/RECORD
