Metadata-Version: 2.1
Name: jmp
Version: 0.0.4
Summary: JMP is a Mixed Precision library for JAX.
Home-page: https://github.com/deepmind/jmp
Author: DeepMind
Author-email: jmp-dev-os@google.com
License: Apache 2.0
Classifier: Development Status :: 4 - Beta
Classifier: Intended Audience :: Developers
Classifier: Intended Audience :: Education
Classifier: Intended Audience :: Science/Research
Classifier: License :: OSI Approved :: Apache Software License
Classifier: Programming Language :: Python :: 3
Classifier: Programming Language :: Python :: 3.8
Classifier: Programming Language :: Python :: 3.9
Classifier: Topic :: Scientific/Engineering :: Mathematics
Classifier: Topic :: Software Development :: Libraries :: Python Modules
Classifier: Topic :: Software Development :: Libraries
Provides-Extra: jax
License-File: LICENSE
